tiktoken_ext/openai_public.py
tiktoken-0.7.0.dist-info/LICENSE
tiktoken-0.7.0.dist-info/METADATA
tiktoken-0.7.0.dist-info/RECORD
tiktoken-0.7.0.dist-info/top_level.txt
tiktoken-0.7.0.dist-info/WHEEL
tiktoken/py.typed
tiktoken/_educational.py
tiktoken/load.py
tiktoken/_tiktoken.cpython-312-x86_64-linux-gnu.so
tiktoken/core.py
tiktoken/registry.py
tiktoken/__init__.py
tiktoken/model.py
