Metadata-Version: 2.1
Name: tiktoken
Version: 0.7.0
Summary: tiktoken is a fast BPE tokeniser for use with OpenAI's models
Author: Shantanu Jain
Author-email: shantanu@openai.com
License: MIT License
Project-URL: homepage, https://github.com/openai/tiktoken
Project-URL: repository, https://github.com/openai/tiktoken
Project-URL: changelog, https://github.com/openai/tiktoken/blob/main/CHANGELOG.md
Requires-Python: >=3.8
License-File: LICENSE
Requires-Dist: regex>=2022.1.18
Requires-Dist: requests>=2.26.0
Provides-Extra: blobfile
Requires-Dist: blobfile>=2; extra == "blobfile"
